Workbook

Sheet Sales Data
A1: MALITABRA INVESTMENTS — PDF SALES EXTRACTION
A2: All matching line items from the 24-page PDF. Part 1 and Part 2 are joined by row order; item names are copied exactly from Part 2.
A4: Line # | B4: Receipt DateTime | C4: PDF Date | D4: PDF Time | E4: Shift Date | F4: Shift | G4: Cashier | H4: Department | I4: Type | J4: Currency | K4: Slip# | L4: Item Code | M4: Item Name | N4: Unit Price | O4: Qty | P4: Gross | Q4: Disc | R4: VAT | S4: G.Profit | T4: Net Price | U4: Part 1 Page | V4: Part 2 Page
A5: 1 | B5: 46294.295 | C5: 46294 | D5: 2.2948495 | E5: 46294 | F5: SYS-DAY | G5: LOVE | H5: ADMIN | I5: USD | J5: USD | K5: LOVE260929070436 | L5: J1002 | M5: White Tissue 2ply | N5: 0.81 | O5: 1 | P5: 0.81 | Q5: 0 | R5: 0.13 | S5: 0.43 | T5: 0.94
A6: 2 | B6: 46294.316 | C6: 46294 | D6: 2.3158449 | E6: 46294 | F6: SYS-DAY | G6: LOVE | H6: ADMIN | I6: USD | J6: USD | K6: LOVE260929073449 | L6: 9556564802006 | M6: Carex Ribbed | N6: 2.16 | O6: 1 | P6: 2.16 | Q6: 0 | R6: 0.34 | S6: 2.09 | T6: 2.5
A7: 3 | B7: 46294.334 | C7: 46294 | D7: 2.3342593 | E7: 46294 | F7: SYS-DAY | G7: LOVE | H7: ADMIN | I7: USD | J7: USD | K7: LOVE260929080120 | L7: 5449000062925 | M7: Bonaqua 1.5L | N7: 0.81 | O7: 1 | P7: 0.81 | Q7: 0 | R7: 0.13 | S7: 0.38 | T7: 0.94
A8: 4 | B8: 46294.345 | C8: 46294 | D8: 2.3448843 | E8: 46294 | F8: SYS-DAY | G8: LOVE | H8: ADMIN | I8: USD | J8: USD | K8: LOVE260929081639 | L8: 271B | M8: Dandy Loose Bubblegum | N8: 0.03 | O8: 10 | P8: 0.3 | Q8: 0 | R8: 0.04 | S8: 0.1 | T8: 0.34
A9: 5 | B9: 46294.351 | C9: 46294 | D9: 2.3510995 | E9: 46294 | F9: SYS-DAY | G9: LOVE | H9: ADMIN | I9: USD | J9: USD | K9: LOVE260929082535 | L9: 5449000095572 | M9: Mazoe Blackberry Original 2l | N9: 4.87 | O9: 1 | P9: 4.87 | Q9: 0 | R9: 0.76 | S9: 1 | T9: 5.63
A10: 6 | B10: 46294.351 | C10: 46294 | D10: 2.3512384 | E10: 46294 | F10: SYS-DAY | G10: LOVE | H10: ADMIN | I10: USD | J10: USD | K10: LOVE260929082535 | L10: 6009698815075 | M10: Dendairy 1 Ltre | N10: 2.19 | O10: 1 | P10: 2.19 | Q10: 0 | R10: 0 | S10: 0.57 | T10: 2.19
A11: 7 | B11: 46294.351 | C11: 46294 | D11: 2.3514699 | E11: 46294 | F11: SYS-DAY | G11: LOVE | H11: ADMIN | I11: USD | J11: USD | K11: LOVE260929082535 | L11: 6007421003492 | M11: RED SEAL TABLE SALT 1KG | N11: 0.75 | O11: 1 | P11: 0.75 | Q11: 0 | R11: 0 | S11: 0.34 | T11: 0.75
A12: 8 | B12: 46294.351 | C12: 46294 | D12: 2.3532755 | E12: 46294 | F12: SYS-DAY | G12: LOVE | H12: ADMIN | I12: USD | J12: USD | K12: LOVE260929082535 | L12: A223 | M12: Crystal Toffees | N12: 0.05 | O12: 10 | P12: 0.5 | Q12: 0 | R12: 0.08 | S12: 0.23 | T12: 0.58
A13: 9 | B13: 46294.354 | C13: 46294 | D13: 2.3538079 | E13: 46294 | F13: SYS-DAY | G13: LOVE | H13: ADMIN | I13: USD | J13: USD | K13: LOVE260929082930 | L13: 2202900 | M13: Soft Drink 300ml | N13: 0.43 | O13: 1 | P13: 0.43 | Q13: 0 | R13: 0.07 | S13: 0.41 | T13: 0.5
A14: 10 | B14: 46294.36 | C14: 46294 | D14: 2.3597917 | E14: 46294 | F14: SYS-DAY | G14: LOVE | H14: ADMIN | I14: USD | J14: USD | K14: LOVE260929083806 | L14: 90000000 | M14: Bonaqua Water 500ml | N14: 0.38 | O14: 1 | P14: 0.38 | Q14: 0 | R14: 0.06 | S14: 0.3 | T14: 0.44
A15: 11 | B15: 46294.364 | C15: 46294 | D15: 2.3634954 | E15: 46294 | F15: SYS-DAY | G15: LOVE | H15: ADMIN | I15: USD | J15: USD | K15: LOVE260929084327 | L15: 6007497001323 | M15: Lakkernax Cheese 28g | N15: 0.27 | O15: 3 | P15: 0.81 | Q15: 0 | R15: 0.12 | S15: 0.57 | T15: 0.93
A16: 12 | B16: 46294.368 | C16: 46294 | D16: 2.3677199 | E16: 46294 | F16: SYS-DAY | G16: LOVE | H16: ADMIN | I16: USD | J16: USD | K16: LOVE260929084931 | L16: 6007497001323 | M16: Lakkernax Cheese 28g | N16: 0.27 | O16: 2 | P16: 0.54 | Q16: 0 | R16: 0.08 | S16: 0.38 | T16: 0.62
... A72: 68 | B72: 46294.66 | C72: 46294 | D72: 2.6601273 | E72: 46294 | F72: SYS-DAY | G72: LOVE | H72: ADMIN | I72: USD | J72: USD | K72: LOVE260929155021 | L72: 90000000 | M72: Bonaqua Water 500ml | N72: 0.38 | O72: 2 | P72: 0.76 | Q72: 0 | R72: 0.12 | S72: 0.59 | T72: 0.88
A73: 69 | B73: 46294.661 | C73: 46294 | D73: 2.6613426 | E73: 46294 | F73: SYS-DAY | G73: LOVE | H73: ADMIN | I73: USD | J73: USD | K73: LOVE260929155220 | L73: 6007497001323 | M73: Lakkernax Cheese 28g | N73: 0.27 | O73: 2 | P73: 0.54 | Q73: 0 | R73: 0.08 | S73: 0.38 | T73: 0.62 | U73: 1 | V73: 1
A74: 70 | B74: 46294.661 | C74: 46294 | D74: 2.6640278 | E74: 46294 | F74: SYS-DAY | G74: LOVE | H74: ADMIN | I74: USD | J74: USD | K74: LOVE260929155220 | L74: 90000000 | M74: Bonaqua Water 500ml | N74: 0.38 | O74: 4 | P74: 1.52 | Q74: 0 | R74: 0.24 | S74: 1.19 | T74: 1.76 | U74: 1 | V74: 1
A75: 71 | B75: 46294.661 | C75: 46294 | D75: 2.6652431 | E75: 46294 | F75: SYS-DAY | G75: LOVE | H75: ADMIN | I75: USD | J75: USD | K75: LOVE260929155220 | L75: 271B | M75: Dandy Loose Bubblegum | N75: 0.03 | O75: 2 | P75: 0.06 | Q75: 0 | R75: 0.01 | S75: 0.02 | T75: 0.07 | U75: 1 | V75: 1
A76: 72 | B76: 46294.661 | C76: 46294 | D76: 2.67 | E76: 46294 | F76: SYS-DAY | G76: LOVE | H76: ADMIN | I76: USD | J76: USD | K76: LOVE260929155220 | L76: 5449000188342 | M76: Minute Maid Apple Grape 400ml | N76: 1.08 | O76: 1 | P76: 1.08 | Q76: 0 | R76: 0.17 | S76: 0.26 | T76: 1.25 | U76: 1 | V76: 1
A77: 73 | B77: 46294.661 | C77: 46294 | D77: 2.6705093 | E77: 46294 | F77: SYS-DAY | G77: LOVE | H77: ADMIN | I77: USD | J77: USD | K77: LOVE260929155220 | L77: 9556564814009 | M77: Carex Rough And Tough | N77: 2.16 | O77: 1 | P77: 2.16 | Q77: 0 | R77: 0.34 | S77: 2.09 | T77: 2.5 | U77: 1 | V77: 1
A78: 74 | B78: 46294.685 | C78: 46294 | D78: 2.6854282 | E78: 46294 | F78: SYS-DAY | G78: LOVE | H78: ADMIN | I78: USD | J78: USD | K78: LOVE260929162701 | L78: 5449000062925 | M78: Bonaqua 1.5L | N78: 0.81 | O78: 1 | P78: 0.81 | Q78: 0 | R78: 0.13 | S78: 0.38 | T78: 0.94 | U78: 1 | V78: 1
A79: 75 | B79: 46294.685 | C79: 46294 | D79: 2.6855787 | E79: 46294 | F79: SYS-DAY | G79: LOVE | H79: ADMIN | I79: USD | J79: USD | K79: LOVE260929162701 | L79: 5449000188342 | M79: Minute Maid Apple Grape 400ml | N79: 1.08 | O79: 1 | P79: 1.08 | Q79: 0 | R79: 0.17 | S79: 0.26 | T79: 1.25 | U79: 1 | V79: 1
A80: 76 | B80: 46294.685 | C80: 46294 | D80: 2.6937847 | E80: 46294 | F80: SYS-DAY | G80: LOVE | H80: ADMIN | I80: USD | J80: USD | K80: LOVE260929162701 | L80: 2202900 | M80: Soft Drink 300ml | N80: 0.43 | O80: 1 | P80: 0.43 | Q80: 0 | R80: 0.07 | S80: 0.41 | T80: 0.5 | U80: 1 | V80: 1
A81: 77 | B81: 46294.732 | C81: 46294 | D81: 2.7316782 | E81: 46294 | F81: SYS-DAY | G81: LOVE | H81: ADMIN | I81: USD | J81: USD | K81: LOVE260929173337 | L81: 6007497004225 | M81: Spuds Tomato Ketchup 23g | N81: 0.55 | O81: 1 | P81: 0.55 | Q81: 0 | R81: 0.08 | S81: 0.53 | T81: 0.63 | U81: 1 | V81: 1
A82: 78 | B82: 46294.735 | C82: 46294 | D82: 2.734537 | E82: 46294 | F82: SYS-DAY | G82: LOVE | H82: ADMIN | I82: USD | J82: USD | K82: LOVE260929173744 | L82: 5449000188342 | M82: Minute Maid Apple Grape 400ml | N82: 1.08 | O82: 2 | P82: 2.16 | Q82: 0 | R82: 0.34 | S82: 0.51 | T82: 2.5 | U82: 1 | V82: 1
A83: 79 | B83: 46294.735 | C83: 46294 | D83: 2.7348264 | E83: 46294 | F83: SYS-DAY | G83: LOVE | H83: ADMIN | I83: USD | J83: USD | K83: LOVE260929173744 | L83: 6007497004225 | M83: Spuds Tomato Ketchup 23g | N83: 0.55 | O83: 1 | P83: 0.55 | Q83: 0 | R83: 0.08 | S83: 0.53 | T83: 0.63 | U83: 1 | V83: 1
A84: 80 | B84: 46294.735 | C84: 46294 | D84: 2.7353009 | E84: 46294 | F84: SYS-DAY | G84: LOVE | H84: ADMIN | I84: USD | J84: USD | K84: LOVE260929173744 | L84: 6005572000216 | M84: Dairibord Steri 500ml | N84: 1.25 | O84: 2 | P84: 2.5 | Q84: 0 | R84: 0 | S84: 2.41 | T84: 2.5 | U84: 1 | V84: 1
... A760: 756 | B760: 46298.238 | C760: 46297 | D760: 2.2378472 | E760: 46297 | F760: SYS-NYT | G760: EKWINIKA | H760: ADMIN | I760: USD | J760: USD | K760: EVE261003054231 | L760: J1002 | M760: White Tissue 2ply | N760: 0.81 | O760: 1 | P760: 0.81 | Q760: 0 | R760: 0.13 | S760: 0.43 | T760: 0.94 | U760: 11 | V760: 11

Sheet sales by item by date
A1: SALES BY ITEM BY DATE — SHIFT + CASHIER
A2: Scope: 29/09/2026 SYS-DAY through 01/10/2026 SYS-NYT. SYS-DAY = LOVE; SYS-NYT = EKWINIKA. The Slip# timestamp controls the actual receipt date/time for shift assignment.
A4: Scope Metric | B4: Value
A5: Line items in scope | B5: 543
A6: Units in scope | B6: 837
A7: Gross sales in scope | B7: 708.38
A8: Net sales in scope | B8: 803.37
A10: Shift Date | B10: Shift | C10: Item Name | D10: Qty | E10: Avg Unit Price | F10: Gross | G10: Disc | H10: VAT | I10: G.Profit | J10: Net Sales
A11: 46294 | B11: SYS-DAY | C11: Soft Drink 300ml | D11: 7 | E11: =IFERROR(F11/D11,0) -> 0.43 | F11: 3.01 | G11: 0 | H11: 0.48 | I11: 2.87 | J11: 3.49
A12: 46294 | B12: SYS-DAY | C12: Eversharp Pen | D12: 1 | E12: =IFERROR(F12/D12,0) -> 0.27 | F12: 0.27 | G12: 0 | H12: 0.04 | I12: 0.14 | J12: 0.31
A13: 46294 | B13: SYS-DAY | C13: Dandy Loose Bubblegum | D13: 29 | E13: =IFERROR(F13/D13,0) -> 0.03 | F13: 0.87 | G13: 0 | H13: 0.12 | I13: 0.29 | J13: 0.99
A14: 46294 | B14: SYS-DAY | C14: Coca Cola 2l | D14: 2 | E14: =IFERROR(F14/D14,0) -> 2.16 | F14: 4.32 | G14: 0 | H14: 0.68 | I14: 4.18 | J14: 5
A15: 46294 | B15: SYS-DAY | C15: Bonaqua 1.5L | D15: 5 | E15: =IFERROR(F15/D15,0) -> 0.81 | F15: 4.05 | G15: 0 | H15: 0.65 | I15: 1.9 | J15: 4.7
A16: 46294 | B16: SYS-DAY | C16: Bonaqua 5l | D16: 7 | E16: =IFERROR(F16/D16,0) -> 1.9 | F16: 13.3 | G16: 0 | H16: 2.05 | I16: 12.81 | J16: 15.35
A17: 46294 | B17: SYS-DAY | C17: Mazoe Blackberry Original 2l | D17: 1 | E17: =IFERROR(F17/D17,0) -> 4.87 | F17: 4.87 | G17: 0 | H17: 0.76 | I17: 1 | J17: 5.63
A18: 46294 | B18: SYS-DAY | C18: Stoney Ginger 330mls | D18: 1 | E18: =IFERROR(F18/D18,0) -> 0.81 | F18: 0.81 | G18: 0 | H18: 0.13 | I18: 0.79 | J18: 0.94
A19: 46294 | B19: SYS-DAY | C19: Coke Zero Can 330ml | D19: 1 | E19: =IFERROR(F19/D19,0) -> 0.81 | F19: 0.81 | G19: 0 | H19: 0.13 | I19: 0.79 | J19: 0.94
A20: 46294 | B20: SYS-DAY | C20: Stoney 2l | D20: 1 | E20: =IFERROR(F20/D20,0) -> 2.16 | F20: 2.16 | G20: 0 | H20: 0.34 | I20: 2.08 | J20: 2.5
A21: 46294 | B21: SYS-DAY | C21: Minute Maid Apple Grape 400ml | D21: 7 | E21: =IFERROR(F21/D21,0) -> 1.08 | F21: 7.56 | G21: 0 | H21: 1.18 | I21: 1.8 | J21: 8.74
A22: 46294 | B22: SYS-DAY | C22: Coke Pets 440mls | D22: 5 | E22: =IFERROR(F22/D22,0) -> 0.81 | F22: 4.05 | G22: 0 | H22: 0.63 | I22: 3.93 | J22: 4.68
... A250: 46296 | B250: SYS-NYT | C250: Eggs | D250: 3 | E250: =IFERROR(F250/D250,0) -> 0.31 | F250: 0.93 | G250: 0 | H250: 0 | I250: 0.9 | J250: 0.93
A251: TOTAL (requested shift scope) | D251: =SUM(D11:D250) -> 837 | E251: =IFERROR(F251/D251,0) -> 0.84633214 | F251: =SUM(F11:F250) -> 708.38 | G251: =SUM(G11:G250) -> 0 | H251: =SUM(H11:H250) -> 94.99 | I251: =SUM(I11:I250) -> 509.74 | J251: =SUM(J11:J250) -> 803.37

Sheet Shift Validation
A1: SHIFT VALIDATION / ASSIGNMENT
A3: Cashier | B3: Assigned Shift | C3: Observed Coverage | D3: Assignment Logic
A4: LOVE | B4: SYS-DAY | C4: 07:04–19:31 observed; no post-midnight rows | D4: Day cashier; shift date = actual receipt calendar date
A5: EKWINIKA | B5: SYS-NYT | C5: 18:42–05:42 observed; early-morning rows continue the night shift | D5: Night cashier; before 18:00 is assigned to the previous evening's shift date
A7: Date / handover handling
A8: The PDF Date column is visibly inconsistent after midnight: some rows show the prior calendar date while the Slip# carries the following date. The workbook keeps the PDF Date/Time unchanged in Sales Data, but uses the Slip# timestamp for the canonical Receipt DateTime. Cashier identity then validates the shift, so early-morning EKWINIKA sales stay with SYS-NYT rather than becoming SYS-DAY.
A12: PDF Source Check | B12: Expected | C12: Workbook | D12: Status
A13: Line items | B13: 756 | C13: =COUNTA('Sales Data'!$A$5:$A$760) -> 756 | D13: =IF(C13=B13,"OK","CHECK") -> OK
A14: Qty | B14: 1151 | C14: =SUM('Sales Data'!$O$5:$O$760) -> 1151 | D14: =IF(C14=B14,"OK","CHECK") -> OK
A15: Gross | B15: 997.28 | C15: =SUM('Sales Data'!$P$5:$P$760) -> 997.28 | D15: =IF(C15=B15,"OK","CHECK") -> CHECK
A16: Disc | B16: 0 | C16: =SUM('Sales Data'!$Q$5:$Q$760) -> 0 | D16: =IF(C16=B16,"OK","CHECK") -> OK
A17: VAT | B17: 134.8 | C17: =SUM('Sales Data'!$R$5:$R$760) -> 134.8 | D17: =IF(C17=B17,"OK","CHECK") -> OK
A18: G.Profit | B18: 713.44 | C18: =SUM('Sales Data'!$S$5:$S$760) -> 713.44 | D18: =IF(C18=B18,"OK","CHECK") -> CHECK
A20: Requested Scope Check | B20: Python Extraction | C20: Workbook Formula | D20: Status
A21: Line items | B21: 543 | C21: =COUNTIFS('Sales Data'!$E$5:$E$760,">="&DATE(2026,9,29),'Sales Data'!$E$5:$E$760,"<"&DATE(2026,10,2)) -> 543 | D21: =IF(C21=B21,"OK","CHECK") -> OK
A22: Units | B22: 837 | C22: =SUMIFS('Sales Data'!$O$5:$O$760,'Sales Data'!$E$5:$E$760,">="&DATE(2026,9,29),'Sales Data'!$E$5:$E$760,"<"&DATE(2026,10,2)) -> 837 | D22: =IF(C22=B22,"OK","CHECK") -> OK
A23: Gross | B23: 708.38 | C23: =SUMIFS('Sales Data'!$P$5:$P$760,'Sales Data'!$E$5:$E$760,">="&DATE(2026,9,29),'Sales Data'!$E$5:$E$760,"<"&DATE(2026,10,2)) -> 708.38 | D23: =IF(C23=B23,"OK","CHECK") -> CHECK
A24: Net Sales | B24: 803.37 | C24: =SUMIFS('Sales Data'!$T$5:$T$760,'Sales Data'!$E$5:$E$760,">="&DATE(2026,9,29),'Sales Data'!$E$5:$E$760,"<"&DATE(2026,10,2)) -> 803.37 | D24: =IF(C24=B24,"OK","CHECK") -> CHECK
A26: All item names are copied exactly as printed in Part 2; no renaming, correction, or normalization was performed.
